MANIFEST.in
README.rst
setup.py
django_stored_queryset.egg-info/PKG-INFO
django_stored_queryset.egg-info/SOURCES.txt
django_stored_queryset.egg-info/dependency_links.txt
django_stored_queryset.egg-info/requires.txt
django_stored_queryset.egg-info/top_level.txt
django_stored_queryset.egg-info/zip-safe
stored/__init__.py
stored/queryset.py
test/__init__.py
test/__init__.pyc
test/stored/__init__.py
test/stored/__init__.pyc
test/stored/models.py
test/stored/models.pyc
test/stored/tests.py
test/stored/tests.pyc