Metadata-Version: 1.0
Name: django-stored-queryset
Version: 0.0.2
Summary: pickleable Django QuerySet
Home-page: http://github.com/denz/django-stored-queryset
Author: Denis Mishchishin
Author-email: dennz78@gmail.com
License: Copyright (c) 2011, Denis Mishchishin, dennz78@gmail.com
